condorgame/__init__.py
condorgame/__version__.py
condorgame/constants.py
condorgame/price_provider.py
condorgame/prices.py
condorgame/quarantine.py
condorgame/tracker.py
condorgame/tracker_evaluator.py
condorgame/debug/__init__.py
condorgame/debug/densitytosimulations.py
condorgame/debug/plots.py
condorgame/examples/__init__.py
condorgame/examples/benchmarktracker.py
condorgame/examples/exampletracker.py
condorgame/examples/utils.py
condorgame/utils/__init__.py
condorgame/utils/data.py
condorgame/utils/densitytosimulations.py
condorgame/utils/distributions.py
condorgame/utils/evaluation_utils.py
condorgame/utils/plots.py
condorgame/utils/tracker_analysis.py
condorgame-0.5.3.dist-info/METADATA
condorgame-0.5.3.dist-info/WHEEL
condorgame-0.5.3.dist-info/top_level.txt
condorgame-0.5.3.dist-info/RECORD
