Metadata-Version: 2.4
Name: condorgame
Version: 0.5.3
Summary: A package for participating in the Condor Game on CrunchDAO
Home-page: https://github.com/crunchdao/condorgame
Author: Abdennour BOUTRIG, Alexis Gassmann
Author-email: abdennour.boutrig@crunchdao.com
Keywords: crunchdao,crunch,condor,condor-game
Classifier: Intended Audience :: Developers
Classifier: Programming Language :: Python :: 3.12
Requires-Python: >=3.12
Requires-Dist: pandas
Requires-Dist: requests
Requires-Dist: numpy
Requires-Dist: tqdm
Requires-Dist: densitypdf
Requires-Dist: plotly
Requires-Dist: sortedcontainers
Provides-Extra: test
Requires-Dist: pytest; extra == "test"
Dynamic: author
Dynamic: author-email
Dynamic: classifier
Dynamic: description
Dynamic: description-content-type
Dynamic: home-page
Dynamic: keywords
Dynamic: provides-extra
Dynamic: requires-dist
Dynamic: requires-python
Dynamic: summary
